debugpypi/__init__.py
debugpypi/print_str.py
wenjuanpro/__init__.py
wenjuanpro/print_str.py
wenjuanpro-0.0.1.dist-info/METADATA
wenjuanpro-0.0.1.dist-info/WHEEL
wenjuanpro-0.0.1.dist-info/top_level.txt
wenjuanpro-0.0.1.dist-info/RECORD
