Metadata-Version: 2.1
Name: wenjuanpro
Version: 0.0.1
Summary: PyPI test test test 寻找迷宫宝石
Home-page: https://github.com/
Author: kagome112
Author-email: wenjuan913@sina.com
License: UNKNOWN
Platform: UNKNOWN
Classifier: Programming Language :: Python :: 3
Classifier: License :: OSI Approved :: MIT License
Classifier: Operating System :: OS Independent
